agomax/__init__.py
agomax/compat.py
agomax/config.py
agomax/detector.py
agomax/exceptions.py
agomax/pipeline.py
agomax/py.typed
agomax/tuner.py
agomax/utils.py
agomax/core/__init__.py
agomax/core/ensemble.py
agomax/core/preprocessing.py
agomax/core/threshold.py
agomax/core/tuning.py
agomax-0.2.3.dist-info/LICENSE
agomax-0.2.3.dist-info/METADATA
agomax-0.2.3.dist-info/WHEEL
agomax-0.2.3.dist-info/top_level.txt
agomax-0.2.3.dist-info/RECORD
