Metadata-Version: 2.1
Name: agomax
Version: 0.2.3
Summary: Production-grade unsupervised anomaly detection for drone telemetry
Author-email: Shagun Tembhurne <shagun@example.com>
License: MIT
Project-URL: Homepage, https://github.com/shaguntembhurne/Agomax
Project-URL: Repository, https://github.com/shaguntembhurne/Agomax
Project-URL: Issues, https://github.com/shaguntembhurne/Agomax/issues
Keywords: anomaly-detection,machine-learning,drone,telemetry,unsupervised
Classifier: Development Status :: 4 - Beta
Classifier: Intended Audience :: Developers
Classifier: Intended Audience :: Science/Research
Classifier: License :: OSI Approved :: MIT License
Classifier: Programming Language :: Python :: 3
Classifier: Programming Language :: Python :: 3.8
Classifier: Programming Language :: Python :: 3.9
Classifier: Programming Language :: Python :: 3.10
Classifier: Programming Language :: Python :: 3.11
Classifier: Topic :: Scientific/Engineering :: Artificial Intelligence
Classifier: Topic :: Software Development :: Libraries :: Python Modules
Requires-Python: >=3.8
License-File: LICENSE
Requires-Dist: numpy<2.0.0,>=1.20.0
Requires-Dist: pandas<3.0.0,>=1.3.0
Requires-Dist: scikit-learn<2.0.0,>=1.0.0
Requires-Dist: scipy<2.0.0,>=1.7.0
Requires-Dist: joblib<2.0.0,>=1.0.0
Provides-Extra: dev
Requires-Dist: pytest>=7.0.0; extra == "dev"
Requires-Dist: pytest-cov>=4.0.0; extra == "dev"
Requires-Dist: black>=22.0.0; extra == "dev"
Requires-Dist: isort>=5.0.0; extra == "dev"
Requires-Dist: mypy>=0.990; extra == "dev"
Requires-Dist: flake8>=5.0.0; extra == "dev"
Provides-Extra: viz
Requires-Dist: matplotlib>=3.5.0; extra == "viz"
Requires-Dist: seaborn>=0.11.0; extra == "viz"
